README.rst
setup.py
cffi_utils/__init__.py
cffi_utils/ffi.py
cffi_utils/py2to3.py
cffi_utils/sowrapper.py
cffi_utils.egg-info/PKG-INFO
cffi_utils.egg-info/SOURCES.txt
cffi_utils.egg-info/dependency_links.txt
cffi_utils.egg-info/requires.txt
cffi_utils.egg-info/top_level.txt
cffi_utils.egg-info/zip-safe
cffi_utils/doc/LICENSE-GPLv3.txt
cffi_utils/doc/README.md