Metadata-Version: 1.1
Name: cffi-utils
Version: 0.56
Summary: Utilities to write python wrappers around C code
Home-page: https://github.com/sundarnagarajan/cffi_utils
Author: Sundar Nagarajan
Author-email: UNKNOWN
License: License :: OSI Approved :: GNU Lesser General Public License v3 or later (LGPLv3+)
Download-URL: https://github.com/sundarnagarajan/cffi_utils/tree/0.56
Platform: UNKNOWN
Classifier: Development Status :: 4 - Beta
Classifier: Programming Language :: Python :: 2
Classifier: Programming Language :: Python :: 3
Classifier: Programming Language :: Python :: Implementation :: PyPy
Classifier: License :: OSI Approved :: GNU Lesser General Public License v3 or later (LGPLv3+)
